xia_analytics_sql/__init__.py
xia_analytics_sql/analyzer.cp39-win_amd64.pyd
xia_analytics_sql-0.0.6.dist-info/LICENSE.txt
xia_analytics_sql-0.0.6.dist-info/METADATA
xia_analytics_sql-0.0.6.dist-info/WHEEL
xia_analytics_sql-0.0.6.dist-info/top_level.txt
xia_analytics_sql-0.0.6.dist-info/RECORD
